sysguard/__init__.py
sysguard/audit.py
sysguard/cli.py
sysguard/logging.py
sysguard-0.1.0.dist-info/METADATA
sysguard-0.1.0.dist-info/WHEEL
sysguard-0.1.0.dist-info/entry_points.txt
sysguard-0.1.0.dist-info/top_level.txt
sysguard-0.1.0.dist-info/RECORD
