Metadata-Version: 2.4
Name: sysguard
Version: 0.1.0
Summary: System audit and self-healing CLI tool
Author: Temiloluwa Ogundiran
License: MIT
Requires-Python: >=3.9
Requires-Dist: psutil
